Nachi/Memory/muxes.sv
module NBitThirtyTwoWayMux #(parameter N=1) (A0, A1, A2, A3, A4, A5, A6, A7, A8, A9, A10, A11, A12, A13, A14, A15, A16, A17, A18, A19, A20, A21, A22, A23, A24, A25, A26, A27, A28, A29, A30, A31, S, F);

	input wire [N-1:0] A0, A1, A2, A3, A4, A5, A6, A7, A8, A9, A10, A11, A12, A13, A14, A15, A16, A17, A18, A19, A20, A21, A22, A23, A24, A25, A26, A27, A28, A29, A30, A31;

	wire [N-1:0] B0, B1;
	
	input wire [4:0] S;
	
	output wire [N-1:0] F;
	
	NBitSixteenWayMux #(.N(N)) lowMux (.A0(A0), .A1(A1), .A2(A2), .A3(A3), .A4(A4), .A5(A5), .A6(A6), .A7(A7), .A8(A8), .A9(A9), .A10(A10), .A11(A11), .A12(A12), .A13(A13), .A14(A14), .A15(A15), .S(S[3:0]), .F(B0));
	
	NBitSixteenWayMux #(.N(N)) highMux (.A0(A16), .A1(A17), .A2(A18), .A3(A19), .A4(A20), .A5(A21), .A6(A22), .A7(A23), .A8(A24), .A9(A25), .A10(A26), .A11(A27), .A12(A28), .A13(A29), .A14(A30), .A15(A31), .S(S[3:0]), .F(B1));
	
	NBitTwoWayMux #(.N(N)) finMux(.A(B0), .B(B1), .S(S[4]), .F(F));

endmodule

module NBitSixteenWayMux #(parameter N=1) (A0, A1, A2, A3, A4, A5, A6, A7, A8, A9, A10, A11, A12, A13, A14, A15, S, F);
   //
   // ---------------- PORT DEFINITIONS ----------------
   //
   
   input wire [N-1:0] A0, A1, A2, A3, A4, A5, A6, A7, A8, A9, A10, A11, A12, A13, A14, A15;
   
   wire [N-1:0] B0, B1, B2, B3;
   
   input wire [3:0] S;
   
   output wire [N-1:0] F;
   
   NBitFourWayMux #(.N(N)) mux1 (.A(A0), .B(A1), .C(A2), .D(A3), .S(S[1:0]), .F(B0));
   
   NBitFourWayMux #(.N(N)) mux2 (.A(A4), .B(A5), .C(A6), .D(A7), .S(S[1:0]), .F(B1));
   
   NBitFourWayMux #(.N(N)) mux3 (.A(A8), .B(A9), .C(A10), .D(A11), .S(S[1:0]), .F(B2));
   
   NBitFourWayMux #(.N(N)) mux4 (.A(A12), .B(A13), .C(A14), .D(A15), .S(S[1:0]), .F(B3));
   
   NBitFourWayMux #(.N(N)) muxF (.A(B0), .B(B1), .C(B2), .D(B3), .S(S[3:2]), .F(F));
   
   //
   // ---------------- MODULE DESIGN IMPLEMENTATION ----------------
   //
        
   
endmodule

module NBitFourWayMux #(parameter N=1)(A, B, C, D, S, F);
   //
   // ---------------- PORT DEFINITIONS ----------------
   //
   input wire [N-1:0] A, B, C, D;
   input wire [1:0] S;
   output wire [N-1:0] F;
   
   wire [N-1:0] lowMuxOut, highMuxOut;
   
   //
   // ---------------- MODULE DESIGN IMPLEMENTATION ----------------
   //
        NBitTwoWayMux #(.N(N)) lowMux(.A(A), .B(B), .S(S[0]), .F(lowMuxOut));
        NBitTwoWayMux #(.N(N)) highMux(.A(C), .B(D), .S(S[0]), .F(highMuxOut));
        NBitTwoWayMux #(.N(N)) finMux(.A(lowMuxOut), .B(highMuxOut), .S(S[1]), .F(F));
   
endmodule

module NBitTwoWayMux #(parameter N=1)(A, B, S, F);
   //
   // ---------------- PORT DEFINITIONS ----------------
   //
   
   input wire [N-1:0] A, B;
   input wire S;
   wire [N-1:0] Sn, AS, BS;
   output wire [N-1:0] F;
   
   genvar i;
   
   generate
    for (i = 0; i < N; i = i + 1) begin
        
        not n_i (Sn[i], S);
        and a1_i (AS[i], Sn[i], A[i]);
        and a2_i (BS[i], S, B[i]);
        or o2_i (F[i], AS[i], BS[i]);
    
        //and g_i (F[i], A[i], B[i]);
    end
   endgenerate

endmodule

Nachi/Memory/srLatch2.v
`timescale 1ns / 1ps

module srLatch2 (R, S, Q, Qn);

    input R, S;
    output Q, Qn;
    
    wire R, S, Q, Qn;
    
    nor (Q, R, Qn);
    
    nor (Qn, Q, S);

endmodule

Nachi/Datapath/dLatch4.sv
`timescale 1ns / 1ps
`include "srLatch2.v"

module dLatch4 (D, Clk, R, Q, Qn);

    input D, Clk, R;
    output Q, Qn;
    
    wire D, Clk;
    wire Dn, R, S, R2, R3;
    wire Q, Qn;
    
    srLatch2 srOne (
        .R(R3),
        .S(S),
        .Q(Q),
        .Qn(Qn)
    );
    
    or (R3, R, R2);
    
    and (R2, Clk, Dn);
    
    and (S, Clk, D);
    
    not (Dn, D);

endmodule

Nachi/Memory/dFlipFlop.v
`timescale 1ns / 1ps
`include "dLatch4.v"

module dFlipFlop (D1, Clk, R, Q2, Qn2);

    input D1, Clk, R;
    output Q2, Qn2;
    
    wire D1, R, Clk, ClkN;
    wire Q1, Qn1, Q2, Qn2;
    
    
    not (ClkN, Clk);
    
    dLatch4 Master (
        .D(D1),
        .Clk(ClkN),
        .R(R),
        .Q(Q1),
        .Qn(Qn1)
    );
    
    dLatch4 Slave (
        .D(Q1),
        .Clk(Clk),
        .R(R),
        .Q(Q2),
        .Qn(Qn2)
    );

endmodule

Nachi/Memory/nBitDRegister.v
`include "dFlipFlop.v"


module nBitDRegister #(parameter N=1) (En, D, Clk, R, Q, Qn);

	input En;
    input [N-1:0] D;
    input R, Clk;
    output [N-1:0] Q, Qn;
    
    wire [N-1:0] D;
    wire R, Clk;
    wire [N-1:0] Q, Qn;
	
	and (Clk2, En, Clk); //enables it
	
   genvar i;
   
   generate
    for (i = 0; i < N; i = i + 1) begin
        dFlipFlop dFF (
        .D1(D[i]),
        .Clk(Clk2),
        .R(R),
        .Q2(Q[i]),
        .Qn2(Qn[i])
    	);
    end
	
   endgenerate
	
endmodule

Nachi/Datapath/decoders.sv
module ThirtyTwoWayDecoder (A, S, F);
   //
   // ---------------- PORT DEFINITIONS ----------------
   //
   
   input wire A; 
   input wire [4:0] S;
   output wire [31:0] F;
   
   wire [1:0] B;
   
   TwoWayDecoder premux (.A(A), .S(S[4]), .F(B));
   
   SixteenWayDecoder himux (.A(B[0]), .S(S[3:0]), .F(F[15:0]));
   SixteenWayDecoder lowmux (.A(B[1]), .S(S[3:0]), .F(F[31:16]));
   

endmodule

module SixteenWayDecoder (A, S, F);
   //
   // ---------------- PORT DEFINITIONS ----------------
   //
   
   input wire A; 
   input wire [3:0] S;
   output wire [15:0] F;
   
   wire [3:0] B;
   
   FourWayDecoder premux (.A(A), .S(S[3:2]), .F(B));
   
   FourWayDecoder himux1 (.A(B[0]), .S(S[1:0]), .F(F[3:0]));
   FourWayDecoder himux2 (.A(B[1]), .S(S[1:0]), .F(F[7:4]));
   
   FourWayDecoder lomux1 (.A(B[2]), .S(S[1:0]), .F(F[11:8]));
   FourWayDecoder lomux2 (.A(B[3]), .S(S[1:0]), .F(F[15:12]));

endmodule

module FourWayDecoder (A, S, F);
   //
   // ---------------- PORT DEFINITIONS ----------------
   //
   
   input wire A; 
   input wire [1:0] S;
   output wire [3:0] F;
   
   wire [1:0] B;
   
   TwoWayDecoder premux (.A(A), .S(S[1]), .F(B));
   
   TwoWayDecoder himux (.A(B[0]), .S(S[0]), .F(F[1:0]));
   TwoWayDecoder lomux (.A(B[1]), .S(S[0]), .F(F[3:2]));

endmodule

module TwoWayDecoder (A, S, F);
   //
   // ---------------- PORT DEFINITIONS ----------------
   //
   
   input wire A, S;
   output wire [1:0] F;
   
   wire Sn;
   
   not (Sn, S);
   
   and (F[0], A, Sn);
   and (F[1], A, S);
  
endmodule

Nachi/Datapath/dataMemory.sv
`include "decoders.sv"
`include "nBitDRegister.v"
`include "muxes.sv"

module dataMemory (R, Clock, WriteEn, Addy, WriteData, ReadData);


	input wire [4:0] Addy; //read/write address
	input wire R, WriteEn, Clock;
	input wire [31:0] WriteData;
	
	wire [1023:0] Q;
	wire [1023:0] Qn;
	wire [31:0] enables;
	
	output wire [31:0] ReadData;
	
	
	ThirtyTwoWayDecoder dechode (
		.A(WriteEn), 
		.S(Addy), 
		.F(enables)
	);
	
	genvar i;
	
	generate
	
    for (i = 0; i < 32; i = i + 1) begin
	
		nBitDRegister #(.N(32)) register1 (
			.En(enables[i]), 
			.D(WriteData), 
			.Clk(Clock), 
			.R(R),   //df reset
			.Q(Q[32*i+31:32*i]), 
			.Qn(Qn[32*i+31:32*i])
		);
		
	end
	
	endgenerate
	
	
	NBitThirtyTwoWayMux #(.N(32)) readMux (
    .A0(Q[31:0]),
    .A1(Q[63:32]),
    .A2(Q[95:64]),
    .A3(Q[127:96]),
    .A4(Q[159:128]),
    .A5(Q[191:160]),
    .A6(Q[223:192]),
    .A7(Q[255:224]),
    .A8(Q[287:256]),
    .A9(Q[319:288]),
    .A10(Q[351:320]),
    .A11(Q[383:352]),
    .A12(Q[415:384]),
    .A13(Q[447:416]),
    .A14(Q[479:448]),
    .A15(Q[511:480]),
    .A16(Q[543:512]),
    .A17(Q[575:544]),
    .A18(Q[607:576]),
    .A19(Q[639:608]),
    .A20(Q[671:640]),
    .A21(Q[703:672]),
    .A22(Q[735:704]),
    .A23(Q[767:736]),
    .A24(Q[799:768]),
    .A25(Q[831:800]),
    .A26(Q[863:832]),
    .A27(Q[895:864]),
    .A28(Q[927:896]),
    .A29(Q[959:928]),
    .A30(Q[991:960]),
    .A31(Q[1023:992]),
    .S(Addy),
    .F(ReadData));
	
endmodule

Nachi/Memory/dataMemory_tb.sv
`timescale 1ns / 1ps
`include "dataMemory.sv"

module dataMemory_tb;

    reg [31:0] D;
    reg r, Clk, En;
	reg [4:0] addy;
    wire [31:0] Q;
	
	reg [5:0] count;
    
    initial
        $monitor ("D = %d, Clk = %b, addy = %b, Q = %b", D, Clk, addy, Q);
    
    initial
    begin
    
        #0
		r = 1'b1; //reset at start up
		
		#10
		r = 1'b0;
		En = 1;
        D = 7;
		addy = 1;
        Clk = 1'b0;
		
		for (count = 0; count <= 31; count = count + 1) begin
   			
			#10
			En = 1;
        	D = count;
			addy = count;
        	Clk = 1'b0;
			
			#10
			En = 1;
        	D = count;
			addy = count;
        	Clk = 1'b1;
   		end
		
		#10
			En = 1;
        	D = 2147483647;
			addy = 1;
        	Clk = 1'b0;
			
			#10
			En = 1;
        	D = 2147483647;
			addy = 1;
        	Clk = 1'b1;
			
			#10
			En = 1;
        	D = -2147483648;
			addy = count;
        	Clk = 1'b0;
			
			#10
			En = 1;
        	D = -2147483648;
			addy = count;
        	Clk = 1'b1;
		
        
    end
    
    initial
    begin
        $dumpfile("waveForm.vcd");
        
        $dumpvars(1, regF);
    end
	
	dataMemory regF (
		.R(r),  
		.Clock(Clk), 
		.WriteEn(En),
		.Addy(addy),
		.WriteData(D),
		.ReadData(Q)
	);

endmodule

Nachi/Memory/waveForm.vcd
$date
	Thu Oct 12 04:26:38 2023
$end
$version
	Icarus Verilog
$end
$timescale
	1ps
$end
$scope module dataMemory_tb $end
$scope module regF $end
$var wire 5 ! Addy [4:0] $end
$var wire 1 " Clock $end
$var wire 1 # R $end
$var wire 32 $ WriteData [31:0] $end
$var wire 1 % WriteEn $end
$var wire 32 & enables [31:0] $end
$var wire 32 ' ReadData [31:0] $end
$var wire 1024 ( Qn [1023:0] $end
$var wire 1024 ) Q [1023:0] $end
$upscope $end
$upscope $end
$enddefinitions $end
#0
$dumpvars
b0 )
b1111111111111111111111111111111111111111111111111111111111111111111111111111111111111111111111111111111111111111111111111111111111111111111111111111111111111111111111111111111111111111111111111111111111111111111111111111111111111111111111111111111111111111111111111111111111111111111111111111111111111111111111111111111111111111111111111111111111111111111111111111111111111111111111111111111111111111111111111111111111111111111111111111111111111111111111111111111111111111111111111111111111111111111111111111111111111111111111111111111111111111111111111111111111111111111111111111111111111111111111111111111111111111111111111111111111111111111111111111111111111111111111111111111111111111111111111111111111111111111111111111111111111111111111111111111111111111111111111111111111111111111111111111111111111111111111111111111111111111111111111111111111111111111111111111111111111111111111111111111111111111111111111111111111111111111111111111111111111111111111111111111111111111111111111111111111111111111111111111111111111111 (
b0 '
bx &
x%
bx $
1#
x"
bx !
$end
#10000
b10 &
0"
b1 !
b111 $
1%
0#
#20000
b1 &
b0 !
b0 $
#30000
1"
#40000
b10 &
0"
b1 !
b1 $
#50000
b1 '
b100000000000000000000000000000000 )
b1111111111111111111111111111111111111111111111111111111111111111111111111111111111111111111111111111111111111111111111111111111111111111111111111111111111111111111111111111111111111111111111111111111111111111111111111111111111111111111111111111111111111111111111111111111111111111111111111111111111111111111111111111111111111111111111111111111111111111111111111111111111111111111111111111111111111111111111111111111111111111111111111111111111111111111111111111111111111111111111111111111111111111111111111111111111111111111111111111111111111111111111111111111111111111111111111111111111111111111111111111111111111111111111111111111111111111111111111111111111111111111111111111111111111111111111111111111111111111111111111111111111111111111111111111111111111111111111111111111111111111111111111111111111111111111111111111111111111111111111111111111111111111111111111111111111111111111111111111111111111111111111111111111111111111111111111111111111111111111111111111111111111111111111111111111011111111111111111111111111111111 (
1"
#60000
b0 '
b100 &
0"
b10 !
b10 $
#70000
b10 '
b100000000000000000000000000000000100000000000000000000000000000000 )
b1111111111111111111111111111111111111111111111111111111111111111111111111111111111111111111111111111111111111111111111111111111111111111111111111111111111111111111111111111111111111111111111111111111111111111111111111111111111111111111111111111111111111111111111111111111111111111111111111111111111111111111111111111111111111111111111111111111111111111111111111111111111111111111111111111111111111111111111111111111111111111111111111111111111111111111111111111111111111111111111111111111111111111111111111111111111111111111111111111111111111111111111111111111111111111111111111111111111111111111111111111111111111111111111111111111111111111111111111111111111111111111111111111111111111111111111111111111111111111111111111111111111111111111111111111111111111111111111111111111111111111111111111111111111111111111111111111111111111111111111111111111111111111111111111111111111111111111111111111111111111111111111111111111111111111111111111111111111111111111111011111111111111111111111111111111011111111111111111111111111111111 (
1"
#80000
b0 '
b1000 &
0"
b11 !
b11 $
#90000
b11 '
b11000000000000000000000000000000100000000000000000000000000000000100000000000000000000000000000000 )
b1111111111111111111111111111111111111111111111111111111111111111111111111111111111111111111111111111111111111111111111111111111111111111111111111111111111111111111111111111111111111111111111111111111111111111111111111111111111111111111111111111111111111111111111111111111111111111111111111111111111111111111111111111111111111111111111111111111111111111111111111111111111111111111111111111111111111111111111111111111111111111111111111111111111111111111111111111111111111111111111111111111111111111111111111111111111111111111111111111111111111111111111111111111111111111111111111111111111111111111111111111111111111111111111111111111111111111111111111111111111111111111111111111111111111111111111111111111111111111111111111111111111111111111111111111111111111111111111111111111111111111111111111111111111111111111111111111111111111111111111111111111111111111111111111111111111111111111111111111111111111111111111111111111111111100111111111111111111111111111111011111111111111111111111111111111011111111111111111111111111111111 (
1"
#100000
b0 '
b10000 &
0"
b100 !
b100 $
#110000
b100 '
b10000000000000000000000000000000011000000000000000000000000000000100000000000000000000000000000000100000000000000000000000000000000 )
b1111111111111111111111111111111111111111111111111111111111111111111111111111111111111111111111111111111111111111111111111111111111111111111111111111111111111111111111111111111111111111111111111111111111111111111111111111111111111111111111111111111111111111111111111111111111111111111111111111111111111111111111111111111111111111111111111111111111111111111111111111111111111111111111111111111111111111111111111111111111111111111111111111111111111111111111111111111111111111111111111111111111111111111111111111111111111111111111111111111111111111111111111111111111111111111111111111111111111111111111111111111111111111111111111111111111111111111111111111111111111111111111111111111111111111111111111111111111111111111111111111111111111111111111111111111111111111111111111111111111111111111111111111111111111111111111111111111111111111111111111111111111111111111111111111111111111111111111111111101111111111111111111111111111111100111111111111111111111111111111011111111111111111111111111111111011111111111111111111111111111111 (
1"
#120000
b0 '
b100000 &
0"
b101 !
b101 $
#130000
b101 '
b1010000000000000000000000000000010000000000000000000000000000000011000000000000000000000000000000100000000000000000000000000000000100000000000000000000000000000000 )
b1111111111111111111111111111111111111111111111111111111111111111111111111111111111111111111111111111111111111111111111111111111111111111111111111111111111111111111111111111111111111111111111111111111111111111111111111111111111111111111111111111111111111111111111111111111111111111111111111111111111111111111111111111111111111111111111111111111111111111111111111111111111111111111111111111111111111111111111111111111111111111111111111111111111111111111111111111111111111111111111111111111111111111111111111111111111111111111111111111111111111111111111111111111111111111111111111111111111111111111111111111111111111111111111111111111111111111111111111111111111111111111111111111111111111111111111111111111111111111111111111111111111111111111111111111111111111111111111111111111111111111111111111111111111111111111111111111111111111111111111111111111111111111111110101111111111111111111111111111101111111111111111111111111111111100111111111111111111111111111111011111111111111111111111111111111011111111111111111111111111111111 (
1"
#140000
b0 '
b1000000 &
0"
b110 !
b110 $
#150000
b110 '
b110000000000000000000000000000001010000000000000000000000000000010000000000000000000000000000000011000000000000000000000000000000100000000000000000000000000000000100000000000000000000000000000000 )
b1111111111111111111111111111111111111111111111111111111111111111111111111111111111111111111111111111111111111111111111111111111111111111111111111111111111111111111111111111111111111111111111111111111111111111111111111111111111111111111111111111111111111111111111111111111111111111111111111111111111111111111111111111111111111111111111111111111111111111111111111111111111111111111111111111111111111111111111111111111111111111111111111111111111111111111111111111111111111111111111111111111111111111111111111111111111111111111111111111111111111111111111111111111111111111111111111111111111111111111111111111111111111111111111111111111111111111111111111111111111111111111111111111111111111111111111111111111111111111111111111111111111111111111111111111111111111111111111111111111111111111111111111111111111111111111111111111111111111001111111111111111111111111111110101111111111111111111111111111101111111111111111111111111111111100111111111111111111111111111111011111111111111111111111111111111011111111111111111111111111111111 (
1"
#160000
b0 '
b10000000 &
0"
b111 !
b111 $
#170000
b111 '
b11100000000000000000000000000000110000000000000000000000000000001010000000000000000000000000000010000000000000000000000000000000011000000000000000000000000000000100000000000000000000000000000000100000000000000000000000000000000 )
b1111111111111111111111111111111111111111111111111111111111111111111111111111111111111111111111111111111111111111111111111111111111111111111111111111111111111111111111111111111111111111111111111111111111111111111111111111111111111111111111111111111111111111111111111111111111111111111111111111111111111111111111111111111111111111111111111111111111111111111111111111111111111111111111111111111111111111111111111111111111111111111111111111111111111111111111111111111111111111111111111111111111111111111111111111111111111111111111111111111111111111111111111111111111111111111111111111111111111111111111111111111111111111111111111111111111111111111111111111111111111111111111111111111111111111111111111111111111111111111111111111111111111111111111111111111111111111111111111111111111111111111111111111100011111111111111111111111111111001111111111111111111111111111110101111111111111111111111111111101111111111111111111111111111111100111111111111111111111111111111011111111111111111111111111111111011111111111111111111111111111111 (
1"
#180000
b0 '
b100000000 &
0"
b1000 !
b1000 $
#190000
b1000 '
b10000000000000000000000000000000011100000000000000000000000000000110000000000000000000000000000001010000000000000000000000000000010000000000000000000000000000000011000000000000000000000000000000100000000000000000000000000000000100000000000000000000000000000000 )
b1111111111111111111111111111111111111111111111111111111111111111111111111111111111111111111111111111111111111111111111111111111111111111111111111111111111111111111111111111111111111111111111111111111111111111111111111111111111111111111111111111111111111111111111111111111111111111111111111111111111111111111111111111111111111111111111111111111111111111111111111111111111111111111111111111111111111111111111111111111111111111111111111111111111111111111111111111111111111111111111111111111111111111111111111111111111111111111111111111111111111111111111111111111111111111111111111111111111111111111111111111111111111111111111111111111111111111111111111111111111111111111111111111111111111111111111111111111111111111111111111111111111111111111111111111111111111111111101111111111111111111111111111111100011111111111111111111111111111001111111111111111111111111111110101111111111111111111111111111101111111111111111111111111111111100111111111111111111111111111111011111111111111111111111111111111011111111111111111111111111111111 (
1"
#200000
b0 '
b1000000000 &
0"
b1001 !
b1001 $
#210000
b1001 '
b1001000000000000000000000000000010000000000000000000000000000000011100000000000000000000000000000110000000000000000000000000000001010000000000000000000000000000010000000000000000000000000000000011000000000000000000000000000000100000000000000000000000000000000100000000000000000000000000000000 )
b1111111111111111111111111111111111111111111111111111111111111111111111111111111111111111111111111111111111111111111111111111111111111111111111111111111111111111111111111111111111111111111111111111111111111111111111111111111111111111111111111111111111111111111111111111111111111111111111111111111111111111111111111111111111111111111111111111111111111111111111111111111111111111111111111111111111111111111111111111111111111111111111111111111111111111111111111111111111111111111111111111111111111111111111111111111111111111111111111111111111111111111111111111111111111111111111111111111111111111111111111111111111111111111111111111111111111111111111111111111111111111111111111111111111111111111111111111111111111111111111111111111111110110111111111111111111111111111101111111111111111111111111111111100011111111111111111111111111111001111111111111111111111111111110101111111111111111111111111111101111111111111111111111111111111100111111111111111111111111111111011111111111111111111111111111111011111111111111111111111111111111 (
1"
#220000
b0 '
b10000000000 &
0"
b1010 !
b1010 $
#230000
b1010 '
b101000000000000000000000000000001001000000000000000000000000000010000000000000000000000000000000011100000000000000000000000000000110000000000000000000000000000001010000000000000000000000000000010000000000000000000000000000000011000000000000000000000000000000100000000000000000000000000000000100000000000000000000000000000000 )
b1111111111111111111111111111111111111111111111111111111111111111111111111111111111111111111111111111111111111111111111111111111111111111111111111111111111111111111111111111111111111111111111111111111111111111111111111111111111111111111111111111111111111111111111111111111111111111111111111111111111111111111111111111111111111111111111111111111111111111111111111111111111111111111111111111111111111111111111111111111111111111111111111111111111111111111111111111111111111111111111111111111111111111111111111111111111111111111111111111111111111111111111111111111111111111111111111111111111111111111111111111111111111111111111111111111111111111111111111111111111111111111111111111111111111111111111111111010111111111111111111111111111110110111111111111111111111111111101111111111111111111111111111111100011111111111111111111111111111001111111111111111111111111111110101111111111111111111111111111101111111111111111111111111111111100111111111111111111111111111111011111111111111111111111111111111011111111111111111111111111111111 (
1"
#240000
b0 '
b100000000000 &
0"
b1011 !
b1011 $
#250000
b1011 '
b10110000000000000000000000000000101000000000000000000000000000001001000000000000000000000000000010000000000000000000000000000000011100000000000000000000000000000110000000000000000000000000000001010000000000000000000000000000010000000000000000000000000000000011000000000000000000000000000000100000000000000000000000000000000100000000000000000000000000000000 )
b1111111111111111111111111111111111111111111111111111111111111111111111111111111111111111111111111111111111111111111111111111111111111111111111111111111111111111111111111111111111111111111111111111111111111111111111111111111111111111111111111111111111111111111111111111111111111111111111111111111111111111111111111111111111111111111111111111111111111111111111111111111111111111111111111111111111111111111111111111111111111111111111111111111111111111111111111111111111111111111111111111111111111111111111111111111111111111111111111111111111111111111111111111111111111111111111111111111111111111111111111111111111111111111111111111111111111111111111111111111111111111111101001111111111111111111111111111010111111111111111111111111111110110111111111111111111111111111101111111111111111111111111111111100011111111111111111111111111111001111111111111111111111111111110101111111111111111111111111111101111111111111111111111111111111100111111111111111111111111111111011111111111111111111111111111111011111111111111111111111111111111 (
1"
#260000
b0 '
b1000000000000 &
0"
b1100 !
b1100 $
#270000
b1100 '
b1100000000000000000000000000000010110000000000000000000000000000101000000000000000000000000000001001000000000000000000000000000010000000000000000000000000000000011100000000000000000000000000000110000000000000000000000000000001010000000000000000000000000000010000000000000000000000000000000011000000000000000000000000000000100000000000000000000000000000000100000000000000000000000000000000 )
b1111111111111111111111111111111111111111111111111111111111111111111111111111111111111111111111111111111111111111111111111111111111111111111111111111111111111111111111111111111111111111111111111111111111111111111111111111111111111111111111111111111111111111111111111111111111111111111111111111111111111111111111111111111111111111111111111111111111111111111111111111111111111111111111111111111111111111111111111111111111111111111111111111111111111111111111111111111111111111111111111111111111111111111111111111111111111111111111111111111111111111111111111111111111111111111111111111111111111111111111111111111111111111111111111111111111110011111111111111111111111111111101001111111111111111111111111111010111111111111111111111111111110110111111111111111111111111111101111111111111111111111111111111100011111111111111111111111111111001111111111111111111111111111110101111111111111111111111111111101111111111111111111111111111111100111111111111111111111111111111011111111111111111111111111111111011111111111111111111111111111111 (
1"
#280000
b0 '
b10000000000000 &
0"
b1101 !
b1101 $
#290000
b1101 '
b110100000000000000000000000000001100000000000000000000000000000010110000000000000000000000000000101000000000000000000000000000001001000000000000000000000000000010000000000000000000000000000000011100000000000000000000000000000110000000000000000000000000000001010000000000000000000000000000010000000000000000000000000000000011000000000000000000000000000000100000000000000000000000000000000100000000000000000000000000000000 )
b1111111111111111111111111111111111111111111111111111111111111111111111111111111111111111111111111111111111111111111111111111111111111111111111111111111111111111111111111111111111111111111111111111111111111111111111111111111111111111111111111111111111111111111111111111111111111111111111111111111111111111111111111111111111111111111111111111111111111111111111111111111111111111111111111111111111111111111111111111111111111111111111111111111111111111111111111111111111111111111111111111111111111111111111111111111111111111111111111111111111111111111111111111111111111111111111111111111111111111111111111111001011111111111111111111111111110011111111111111111111111111111101001111111111111111111111111111010111111111111111111111111111110110111111111111111111111111111101111111111111111111111111111111100011111111111111111111111111111001111111111111111111111111111110101111111111111111111111111111101111111111111111111111111111111100111111111111111111111111111111011111111111111111111111111111111011111111111111111111111111111111 (
1"
#300000
b0 '
b100000000000000 &
0"
b1110 !
b1110 $
#310000
b1110 '
b11100000000000000000000000000000110100000000000000000000000000001100000000000000000000000000000010110000000000000000000000000000101000000000000000000000000000001001000000000000000000000000000010000000000000000000000000000000011100000000000000000000000000000110000000000000000000000000000001010000000000000000000000000000010000000000000000000000000000000011000000000000000000000000000000100000000000000000000000000000000100000000000000000000000000000000 )
b1111111111111111111111111111111111111111111111111111111111111111111111111111111111111111111111111111111111111111111111111111111111111111111111111111111111111111111111111111111111111111111111111111111111111111111111111111111111111111111111111111111111111111111111111111111111111111111111111111111111111111111111111111111111111111111111111111111111111111111111111111111111111111111111111111111111111111111111111111111111111111111111111111111111111111111111111111111111111111111111111111111111111111111111111111111111111111111111111111111111111111111111111111111111111111111100011111111111111111111111111111001011111111111111111111111111110011111111111111111111111111111101001111111111111111111111111111010111111111111111111111111111110110111111111111111111111111111101111111111111111111111111111111100011111111111111111111111111111001111111111111111111111111111110101111111111111111111111111111101111111111111111111111111111111100111111111111111111111111111111011111111111111111111111111111111011111111111111111111111111111111 (
1"
#320000
b0 '
b1000000000000000 &
0"
b1111 !
b1111 $
#330000
b1111 '
b1111000000000000000000000000000011100000000000000000000000000000110100000000000000000000000000001100000000000000000000000000000010110000000000000000000000000000101000000000000000000000000000001001000000000000000000000000000010000000000000000000000000000000011100000000000000000000000000000110000000000000000000000000000001010000000000000000000000000000010000000000000000000000000000000011000000000000000000000000000000100000000000000000000000000000000100000000000000000000000000000000 )
b1111111111111111111111111111111111111111111111111111111111111111111111111111111111111111111111111111111111111111111111111111111111111111111111111111111111111111111111111111111111111111111111111111111111111111111111111111111111111111111111111111111111111111111111111111111111111111111111111111111111111111111111111111111111111111111111111111111111111111111111111111111111111111111111111111111111111111111111111111111111111111111111111111111111111111111111111111111111111111111111111111111111111111111111111111111111111111111111111111111111110000111111111111111111111111111100011111111111111111111111111111001011111111111111111111111111110011111111111111111111111111111101001111111111111111111111111111010111111111111111111111111111110110111111111111111111111111111101111111111111111111111111111111100011111111111111111111111111111001111111111111111111111111111110101111111111111111111111111111101111111111111111111111111111111100111111111111111111111111111111011111111111111111111111111111111011111111111111111111111111111111 (
1"
#340000
b0 '
b10000000000000000 &
0"
b10000 !
b10000 $
#350000
b10000 '
b1000000000000000000000000000000001111000000000000000000000000000011100000000000000000000000000000110100000000000000000000000000001100000000000000000000000000000010110000000000000000000000000000101000000000000000000000000000001001000000000000000000000000000010000000000000000000000000000000011100000000000000000000000000000110000000000000000000000000000001010000000000000000000000000000010000000000000000000000000000000011000000000000000000000000000000100000000000000000000000000000000100000000000000000000000000000000 )
b1111111111111111111111111111111111111111111111111111111111111111111111111111111111111111111111111111111111111111111111111111111111111111111111111111111111111111111111111111111111111111111111111111111111111111111111111111111111111111111111111111111111111111111111111111111111111111111111111111111111111111111111111111111111111111111111111111111111111111111111111111111111111111111111111111111111111111111111111111111111111111111111111111111111111111111111111111111111111111111111111111111111111111111111111110111111111111111111111111111111110000111111111111111111111111111100011111111111111111111111111111001011111111111111111111111111110011111111111111111111111111111101001111111111111111111111111111010111111111111111111111111111110110111111111111111111111111111101111111111111111111111111111111100011111111111111111111111111111001111111111111111111111111111110101111111111111111111111111111101111111111111111111111111111111100111111111111111111111111111111011111111111111111111111111111111011111111111111111111111111111111 (
1"
#360000
b0 '
b100000000000000000 &
0"
b10001 !
b10001 $
#370000
b10001 '
b100010000000000000000000000000001000000000000000000000000000000001111000000000000000000000000000011100000000000000000000000000000110100000000000000000000000000001100000000000000000000000000000010110000000000000000000000000000101000000000000000000000000000001001000000000000000000000000000010000000000000000000000000000000011100000000000000000000000000000110000000000000000000000000000001010000000000000000000000000000010000000000000000000000000000000011000000000000000000000000000000100000000000000000000000000000000100000000000000000000000000000000 )
b1111111111111111111111111111111111111111111111111111111111111111111111111111111111111111111111111111111111111111111111111111111111111111111111111111111111111111111111111111111111111111111111111111111111111111111111111111111111111111111111111111111111111111111111111111111111111111111111111111111111111111111111111111111111111111111111111111111111111111111111111111111111111111111111111111111111111111111111111111111111111111111111111111111111111111111111111111111111111111111011101111111111111111111111111110111111111111111111111111111111110000111111111111111111111111111100011111111111111111111111111111001011111111111111111111111111110011111111111111111111111111111101001111111111111111111111111111010111111111111111111111111111110110111111111111111111111111111101111111111111111111111111111111100011111111111111111111111111111001111111111111111111111111111110101111111111111111111111111111101111111111111111111111111111111100111111111111111111111111111111011111111111111111111111111111111011111111111111111111111111111111 (
1"
#380000
b0 '
b1000000000000000000 &
0"
b10010 !
b10010 $
